{
  "coordinate_model": "selected_old_pair_to_p0_zero_p1_e1",
  "pattern": "offset5-postunit42-8m-full",
  "reports": [
    {
      "elapsed_seconds": 0.3481650830071885,
      "expanded_polynomial_sha256": "fd74a4c41abe00978bd36ad8a8ff6a689105d19b6da52128abdea65e55608729",
      "msolve": {
        "forward": {
          "output_char_count": 17,
          "output_sha256": "6adf16fd42fd52884a1f6c68aa5f2958952d4026d6d4238b33ddb2fe21e9d75f",
          "returncode": 0,
          "stderr": "",
          "verdict": "NONUNIT"
        },
        "reverse": {
          "output_char_count": 17,
          "output_sha256": "6adf16fd42fd52884a1f6c68aa5f2958952d4026d6d4238b33ddb2fe21e9d75f",
          "returncode": 0,
          "stderr": "",
          "verdict": "NONUNIT"
        }
      },
      "old_anchor_pair": [
        0,
        1
      ],
      "old_to_new": [
        0,
        1,
        2,
        3,
        4,
        5,
        6,
        7,
        8,
        9,
        10,
        11
      ]
    },
    {
      "elapsed_seconds": 0.3509380419855006,
      "expanded_polynomial_sha256": "1afc833441d115d4bf07b7ffb0578cfa2e365335887c19a2dd7515a9f1266330",
      "msolve": {
        "forward": {
          "output_char_count": 17,
          "output_sha256": "6adf16fd42fd52884a1f6c68aa5f2958952d4026d6d4238b33ddb2fe21e9d75f",
          "returncode": 0,
          "stderr": "",
          "verdict": "NONUNIT"
        },
        "reverse": {
          "output_char_count": 17,
          "output_sha256": "6adf16fd42fd52884a1f6c68aa5f2958952d4026d6d4238b33ddb2fe21e9d75f",
          "returncode": 0,
          "stderr": "",
          "verdict": "NONUNIT"
        }
      },
      "old_anchor_pair": [
        0,
        2
      ],
      "old_to_new": [
        0,
        2,
        1,
        3,
        4,
        5,
        6,
        7,
        8,
        9,
        10,
        11
      ]
    },
    {
      "elapsed_seconds": 0.3754774999979418,
      "expanded_polynomial_sha256": "f98326b9dcbbfae632acfffb5c7a0402ff7662de1fb1b23f1018c0c23772e609",
      "msolve": {
        "forward": {
          "output_char_count": 17,
          "output_sha256": "6adf16fd42fd52884a1f6c68aa5f2958952d4026d6d4238b33ddb2fe21e9d75f",
          "returncode": 0,
          "stderr": "",
          "verdict": "NONUNIT"
        },
        "reverse": {
          "output_char_count": 17,
          "output_sha256": "6adf16fd42fd52884a1f6c68aa5f2958952d4026d6d4238b33ddb2fe21e9d75f",
          "returncode": 0,
          "stderr": "",
          "verdict": "NONUNIT"
        }
      },
      "old_anchor_pair": [
        0,
        3
      ],
      "old_to_new": [
        0,
        2,
        3,
        1,
        4,
        5,
        6,
        7,
        8,
        9,
        10,
        11
      ]
    },
    {
      "elapsed_seconds": 0.075234875024762,
      "expanded_polynomial_sha256": "2dabe127df53bc5aa57386f696d4b71696d342f1c36252fed12c4d3da3bc1df2",
      "msolve": {
        "forward": {
          "output_char_count": 17,
          "output_sha256": "6adf16fd42fd52884a1f6c68aa5f2958952d4026d6d4238b33ddb2fe21e9d75f",
          "returncode": 0,
          "stderr": "",
          "verdict": "NONUNIT"
        },
        "reverse": {
          "output_char_count": 17,
          "output_sha256": "6adf16fd42fd52884a1f6c68aa5f2958952d4026d6d4238b33ddb2fe21e9d75f",
          "returncode": 0,
          "stderr": "",
          "verdict": "NONUNIT"
        }
      },
      "old_anchor_pair": [
        0,
        4
      ],
      "old_to_new": [
        0,
        2,
        3,
        4,
        1,
        5,
        6,
        7,
        8,
        9,
        10,
        11
      ]
    },
    {
      "elapsed_seconds": 0.2364533749932889,
      "expanded_polynomial_sha256": "e942e3b4b6725e3c374f739483accd965062e6b0d680993e5bf9f3fea3c74a2a",
      "msolve": {
        "forward": {
          "output_char_count": 17,
          "output_sha256": "6adf16fd42fd52884a1f6c68aa5f2958952d4026d6d4238b33ddb2fe21e9d75f",
          "returncode": 0,
          "stderr": "",
          "verdict": "NONUNIT"
        },
        "reverse": {
          "output_char_count": 17,
          "output_sha256": "6adf16fd42fd52884a1f6c68aa5f2958952d4026d6d4238b33ddb2fe21e9d75f",
          "returncode": 0,
          "stderr": "",
          "verdict": "NONUNIT"
        }
      },
      "old_anchor_pair": [
        0,
        5
      ],
      "old_to_new": [
        0,
        2,
        3,
        4,
        5,
        1,
        6,
        7,
        8,
        9,
        10,
        11
      ]
    },
    {
      "elapsed_seconds": 0.11255554200033657,
      "expanded_polynomial_sha256": "b7c24abfda35573bcbd0516061be5d7f6e260559094b25d385bb7d1c9fb44139",
      "msolve": {
        "forward": {
          "output_char_count": 17,
          "output_sha256": "6adf16fd42fd52884a1f6c68aa5f2958952d4026d6d4238b33ddb2fe21e9d75f",
          "returncode": 0,
          "stderr": "",
          "verdict": "NONUNIT"
        },
        "reverse": {
          "output_char_count": 17,
          "output_sha256": "6adf16fd42fd52884a1f6c68aa5f2958952d4026d6d4238b33ddb2fe21e9d75f",
          "returncode": 0,
          "stderr": "",
          "verdict": "NONUNIT"
        }
      },
      "old_anchor_pair": [
        0,
        6
      ],
      "old_to_new": [
        0,
        2,
        3,
        4,
        5,
        6,
        1,
        7,
        8,
        9,
        10,
        11
      ]
    },
    {
      "elapsed_seconds": 0.30114174998016097,
      "expanded_polynomial_sha256": "463b9593dc0ec04382952a0a61e4d3bb6048ca8f0458902b30d452e23d962e27",
      "msolve": {
        "forward": {
          "output_char_count": 17,
          "output_sha256": "6adf16fd42fd52884a1f6c68aa5f2958952d4026d6d4238b33ddb2fe21e9d75f",
          "returncode": 0,
          "stderr": "",
          "verdict": "NONUNIT"
        },
        "reverse": {
          "output_char_count": 17,
          "output_sha256": "6adf16fd42fd52884a1f6c68aa5f2958952d4026d6d4238b33ddb2fe21e9d75f",
          "returncode": 0,
          "stderr": "",
          "verdict": "NONUNIT"
        }
      },
      "old_anchor_pair": [
        0,
        7
      ],
      "old_to_new": [
        0,
        2,
        3,
        4,
        5,
        6,
        7,
        1,
        8,
        9,
        10,
        11
      ]
    },
    {
      "elapsed_seconds": 0.3806103329989128,
      "expanded_polynomial_sha256": "c5ae57a55cf6f3b4785769473cb91f21d3e7bd26d705eff711d7f3dcfb717b21",
      "msolve": {
        "forward": {
          "output_char_count": 17,
          "output_sha256": "6adf16fd42fd52884a1f6c68aa5f2958952d4026d6d4238b33ddb2fe21e9d75f",
          "returncode": 0,
          "stderr": "",
          "verdict": "NONUNIT"
        },
        "reverse": {
          "output_char_count": 17,
          "output_sha256": "6adf16fd42fd52884a1f6c68aa5f2958952d4026d6d4238b33ddb2fe21e9d75f",
          "returncode": 0,
          "stderr": "",
          "verdict": "NONUNIT"
        }
      },
      "old_anchor_pair": [
        0,
        8
      ],
      "old_to_new": [
        0,
        2,
        3,
        4,
        5,
        6,
        7,
        8,
        1,
        9,
        10,
        11
      ]
    },
    {
      "elapsed_seconds": 0.5295107499987353,
      "expanded_polynomial_sha256": "6d502ca610ff2f64cbd3c3e39beb87daed5a6c9b02d6612f2021bf8be7989591",
      "msolve": {
        "forward": {
          "output_char_count": 17,
          "output_sha256": "6adf16fd42fd52884a1f6c68aa5f2958952d4026d6d4238b33ddb2fe21e9d75f",
          "returncode": 0,
          "stderr": "",
          "verdict": "NONUNIT"
        },
        "reverse": {
          "output_char_count": 17,
          "output_sha256": "6adf16fd42fd52884a1f6c68aa5f2958952d4026d6d4238b33ddb2fe21e9d75f",
          "returncode": 0,
          "stderr": "",
          "verdict": "NONUNIT"
        }
      },
      "old_anchor_pair": [
        0,
        9
      ],
      "old_to_new": [
        0,
        2,
        3,
        4,
        5,
        6,
        7,
        8,
        9,
        1,
        10,
        11
      ]
    },
    {
      "elapsed_seconds": 0.4880102919996716,
      "expanded_polynomial_sha256": "f1976561bedd298e09f2fade699a37abd077546c959558faace3974c817a2e9b",
      "msolve": {
        "forward": {
          "output_char_count": 17,
          "output_sha256": "6adf16fd42fd52884a1f6c68aa5f2958952d4026d6d4238b33ddb2fe21e9d75f",
          "returncode": 0,
          "stderr": "",
          "verdict": "NONUNIT"
        },
        "reverse": {
          "output_char_count": 17,
          "output_sha256": "6adf16fd42fd52884a1f6c68aa5f2958952d4026d6d4238b33ddb2fe21e9d75f",
          "returncode": 0,
          "stderr": "",
          "verdict": "NONUNIT"
        }
      },
      "old_anchor_pair": [
        0,
        10
      ],
      "old_to_new": [
        0,
        2,
        3,
        4,
        5,
        6,
        7,
        8,
        9,
        10,
        1,
        11
      ]
    },
    {
      "elapsed_seconds": 0.33747075000428595,
      "expanded_polynomial_sha256": "dab6f9722f8a00f80bfe99396b2d56950fffd4e78353450ac5935a9857c7ad82",
      "msolve": {
        "forward": {
          "output_char_count": 17,
          "output_sha256": "6adf16fd42fd52884a1f6c68aa5f2958952d4026d6d4238b33ddb2fe21e9d75f",
          "returncode": 0,
          "stderr": "",
          "verdict": "NONUNIT"
        },
        "reverse": {
          "output_char_count": 17,
          "output_sha256": "6adf16fd42fd52884a1f6c68aa5f2958952d4026d6d4238b33ddb2fe21e9d75f",
          "returncode": 0,
          "stderr": "",
          "verdict": "NONUNIT"
        }
      },
      "old_anchor_pair": [
        0,
        11
      ],
      "old_to_new": [
        0,
        2,
        3,
        4,
        5,
        6,
        7,
        8,
        9,
        10,
        11,
        1
      ]
    },
    {
      "elapsed_seconds": 0.30914966700947843,
      "expanded_polynomial_sha256": "699001ef17b748e5413fb46e8ab65e66486c6745cc2dea6c497cfa1375846185",
      "msolve": {
        "forward": {
          "output_char_count": 17,
          "output_sha256": "6adf16fd42fd52884a1f6c68aa5f2958952d4026d6d4238b33ddb2fe21e9d75f",
          "returncode": 0,
          "stderr": "",
          "verdict": "NONUNIT"
        },
        "reverse": {
          "output_char_count": 17,
          "output_sha256": "6adf16fd42fd52884a1f6c68aa5f2958952d4026d6d4238b33ddb2fe21e9d75f",
          "returncode": 0,
          "stderr": "",
          "verdict": "NONUNIT"
        }
      },
      "old_anchor_pair": [
        1,
        2
      ],
      "old_to_new": [
        2,
        0,
        1,
        3,
        4,
        5,
        6,
        7,
        8,
        9,
        10,
        11
      ]
    },
    {
      "elapsed_seconds": 0.11336362501606345,
      "expanded_polynomial_sha256": "9a50958eb22ecc84148455c35807ef7ae473e0eb990312ac339c1115ba2fb316",
      "msolve": {
        "forward": {
          "output_char_count": 6,
          "output_sha256": "0333251e6ebb3890ef547f522ec55f27f0cef9a860998757e31f3e1b819e7490",
          "returncode": 0,
          "stderr": "",
          "verdict": "UNIT"
        },
        "reverse": {
          "output_char_count": 6,
          "output_sha256": "0333251e6ebb3890ef547f522ec55f27f0cef9a860998757e31f3e1b819e7490",
          "returncode": 0,
          "stderr": "",
          "verdict": "UNIT"
        }
      },
      "old_anchor_pair": [
        1,
        3
      ],
      "old_to_new": [
        2,
        0,
        3,
        1,
        4,
        5,
        6,
        7,
        8,
        9,
        10,
        11
      ]
    },
    {
      "elapsed_seconds": 0.09513708300073631,
      "expanded_polynomial_sha256": "c0354af75c0d78fde69a8d4cc4671e279706fc44a7ab27d43ad377389c227905",
      "msolve": {
        "forward": {
          "output_char_count": 17,
          "output_sha256": "6adf16fd42fd52884a1f6c68aa5f2958952d4026d6d4238b33ddb2fe21e9d75f",
          "returncode": 0,
          "stderr": "",
          "verdict": "NONUNIT"
        },
        "reverse": {
          "output_char_count": 17,
          "output_sha256": "6adf16fd42fd52884a1f6c68aa5f2958952d4026d6d4238b33ddb2fe21e9d75f",
          "returncode": 0,
          "stderr": "",
          "verdict": "NONUNIT"
        }
      },
      "old_anchor_pair": [
        1,
        4
      ],
      "old_to_new": [
        2,
        0,
        3,
        4,
        1,
        5,
        6,
        7,
        8,
        9,
        10,
        11
      ]
    },
    {
      "elapsed_seconds": 0.12465779201011173,
      "expanded_polynomial_sha256": "be586160aaf8d6c0fdce4c045abd81bd17de2fa88cae6a1aab7a58e4140a23f3",
      "msolve": {
        "forward": {
          "output_char_count": 6,
          "output_sha256": "0333251e6ebb3890ef547f522ec55f27f0cef9a860998757e31f3e1b819e7490",
          "returncode": 0,
          "stderr": "",
          "verdict": "UNIT"
        },
        "reverse": {
          "output_char_count": 6,
          "output_sha256": "0333251e6ebb3890ef547f522ec55f27f0cef9a860998757e31f3e1b819e7490",
          "returncode": 0,
          "stderr": "",
          "verdict": "UNIT"
        }
      },
      "old_anchor_pair": [
        1,
        5
      ],
      "old_to_new": [
        2,
        0,
        3,
        4,
        5,
        1,
        6,
        7,
        8,
        9,
        10,
        11
      ]
    },
    {
      "elapsed_seconds": 0.1078954580007121,
      "expanded_polynomial_sha256": "de9d2a370e8db8069bb2d869ce9da8cf704536398cbed13557045a1751b298fe",
      "msolve": {
        "forward": {
          "output_char_count": 6,
          "output_sha256": "0333251e6ebb3890ef547f522ec55f27f0cef9a860998757e31f3e1b819e7490",
          "returncode": 0,
          "stderr": "",
          "verdict": "UNIT"
        },
        "reverse": {
          "output_char_count": 6,
          "output_sha256": "0333251e6ebb3890ef547f522ec55f27f0cef9a860998757e31f3e1b819e7490",
          "returncode": 0,
          "stderr": "",
          "verdict": "UNIT"
        }
      },
      "old_anchor_pair": [
        1,
        6
      ],
      "old_to_new": [
        2,
        0,
        3,
        4,
        5,
        6,
        1,
        7,
        8,
        9,
        10,
        11
      ]
    },
    {
      "elapsed_seconds": 0.284589374990901,
      "expanded_polynomial_sha256": "e9e5cc63fb93566ca2efea87574dc23395e3285770182492afc6e2a3e04c83d6",
      "msolve": {
        "forward": {
          "output_char_count": 17,
          "output_sha256": "6adf16fd42fd52884a1f6c68aa5f2958952d4026d6d4238b33ddb2fe21e9d75f",
          "returncode": 0,
          "stderr": "",
          "verdict": "NONUNIT"
        },
        "reverse": {
          "output_char_count": 17,
          "output_sha256": "6adf16fd42fd52884a1f6c68aa5f2958952d4026d6d4238b33ddb2fe21e9d75f",
          "returncode": 0,
          "stderr": "",
          "verdict": "NONUNIT"
        }
      },
      "old_anchor_pair": [
        1,
        7
      ],
      "old_to_new": [
        2,
        0,
        3,
        4,
        5,
        6,
        7,
        1,
        8,
        9,
        10,
        11
      ]
    },
    {
      "elapsed_seconds": 0.2845611660159193,
      "expanded_polynomial_sha256": "6b92c45ca6ba5c3a4e91b42d942e45b2c0970e607f42ee804834089330338123",
      "msolve": {
        "forward": {
          "output_char_count": 17,
          "output_sha256": "6adf16fd42fd52884a1f6c68aa5f2958952d4026d6d4238b33ddb2fe21e9d75f",
          "returncode": 0,
          "stderr": "",
          "verdict": "NONUNIT"
        },
        "reverse": {
          "output_char_count": 17,
          "output_sha256": "6adf16fd42fd52884a1f6c68aa5f2958952d4026d6d4238b33ddb2fe21e9d75f",
          "returncode": 0,
          "stderr": "",
          "verdict": "NONUNIT"
        }
      },
      "old_anchor_pair": [
        1,
        8
      ],
      "old_to_new": [
        2,
        0,
        3,
        4,
        5,
        6,
        7,
        8,
        1,
        9,
        10,
        11
      ]
    },
    {
      "elapsed_seconds": 0.2758066249953117,
      "expanded_polynomial_sha256": "4df0f7f50aabf2421234dc465741c0c3b65cd570875237297ef66efefd4c82c5",
      "msolve": {
        "forward": {
          "output_char_count": 17,
          "output_sha256": "6adf16fd42fd52884a1f6c68aa5f2958952d4026d6d4238b33ddb2fe21e9d75f",
          "returncode": 0,
          "stderr": "",
          "verdict": "NONUNIT"
        },
        "reverse": {
          "output_char_count": 17,
          "output_sha256": "6adf16fd42fd52884a1f6c68aa5f2958952d4026d6d4238b33ddb2fe21e9d75f",
          "returncode": 0,
          "stderr": "",
          "verdict": "NONUNIT"
        }
      },
      "old_anchor_pair": [
        1,
        9
      ],
      "old_to_new": [
        2,
        0,
        3,
        4,
        5,
        6,
        7,
        8,
        9,
        1,
        10,
        11
      ]
    },
    {
      "elapsed_seconds": 0.3541566669882741,
      "expanded_polynomial_sha256": "b448c20d768c9e65d5a39f4515fc0915af7a68b874e9606d1f204779db161796",
      "msolve": {
        "forward": {
          "output_char_count": 17,
          "output_sha256": "6adf16fd42fd52884a1f6c68aa5f2958952d4026d6d4238b33ddb2fe21e9d75f",
          "returncode": 0,
          "stderr": "",
          "verdict": "NONUNIT"
        },
        "reverse": {
          "output_char_count": 17,
          "output_sha256": "6adf16fd42fd52884a1f6c68aa5f2958952d4026d6d4238b33ddb2fe21e9d75f",
          "returncode": 0,
          "stderr": "",
          "verdict": "NONUNIT"
        }
      },
      "old_anchor_pair": [
        1,
        10
      ],
      "old_to_new": [
        2,
        0,
        3,
        4,
        5,
        6,
        7,
        8,
        9,
        10,
        1,
        11
      ]
    },
    {
      "elapsed_seconds": 0.30134974999236874,
      "expanded_polynomial_sha256": "c930afd228e8efe7a933aac6dd6764ca24598da35850711853d1a589ed13c266",
      "msolve": {
        "forward": {
          "output_char_count": 17,
          "output_sha256": "6adf16fd42fd52884a1f6c68aa5f2958952d4026d6d4238b33ddb2fe21e9d75f",
          "returncode": 0,
          "stderr": "",
          "verdict": "NONUNIT"
        },
        "reverse": {
          "output_char_count": 17,
          "output_sha256": "6adf16fd42fd52884a1f6c68aa5f2958952d4026d6d4238b33ddb2fe21e9d75f",
          "returncode": 0,
          "stderr": "",
          "verdict": "NONUNIT"
        }
      },
      "old_anchor_pair": [
        1,
        11
      ],
      "old_to_new": [
        2,
        0,
        3,
        4,
        5,
        6,
        7,
        8,
        9,
        10,
        11,
        1
      ]
    },
    {
      "elapsed_seconds": 0.265606792003382,
      "expanded_polynomial_sha256": "6c0d52a92bc1f1cb217ec5bdc69b6fc4c01c5b28ac6a4e7c9fd4678b1f498253",
      "msolve": {
        "forward": {
          "output_char_count": 17,
          "output_sha256": "6adf16fd42fd52884a1f6c68aa5f2958952d4026d6d4238b33ddb2fe21e9d75f",
          "returncode": 0,
          "stderr": "",
          "verdict": "NONUNIT"
        },
        "reverse": {
          "output_char_count": 17,
          "output_sha256": "6adf16fd42fd52884a1f6c68aa5f2958952d4026d6d4238b33ddb2fe21e9d75f",
          "returncode": 0,
          "stderr": "",
          "verdict": "NONUNIT"
        }
      },
      "old_anchor_pair": [
        2,
        3
      ],
      "old_to_new": [
        2,
        3,
        0,
        1,
        4,
        5,
        6,
        7,
        8,
        9,
        10,
        11
      ]
    },
    {
      "elapsed_seconds": 0.3186997919983696,
      "expanded_polynomial_sha256": "5ec77860a99a904bfa25c19b12cad92132f9b9b085487e1268bf00186447ab6c",
      "msolve": {
        "forward": {
          "output_char_count": 6,
          "output_sha256": "0333251e6ebb3890ef547f522ec55f27f0cef9a860998757e31f3e1b819e7490",
          "returncode": 0,
          "stderr": "",
          "verdict": "UNIT"
        },
        "reverse": {
          "output_char_count": 6,
          "output_sha256": "0333251e6ebb3890ef547f522ec55f27f0cef9a860998757e31f3e1b819e7490",
          "returncode": 0,
          "stderr": "",
          "verdict": "UNIT"
        }
      },
      "old_anchor_pair": [
        2,
        4
      ],
      "old_to_new": [
        2,
        3,
        0,
        4,
        1,
        5,
        6,
        7,
        8,
        9,
        10,
        11
      ]
    },
    {
      "elapsed_seconds": 0.5187878329888918,
      "expanded_polynomial_sha256": "f52d01b8e33b712c76566c2ca19205384673da173687063bd537821adb4b2c13",
      "msolve": {
        "forward": {
          "output_char_count": 17,
          "output_sha256": "6adf16fd42fd52884a1f6c68aa5f2958952d4026d6d4238b33ddb2fe21e9d75f",
          "returncode": 0,
          "stderr": "",
          "verdict": "NONUNIT"
        },
        "reverse": {
          "output_char_count": 17,
          "output_sha256": "6adf16fd42fd52884a1f6c68aa5f2958952d4026d6d4238b33ddb2fe21e9d75f",
          "returncode": 0,
          "stderr": "",
          "verdict": "NONUNIT"
        }
      },
      "old_anchor_pair": [
        2,
        5
      ],
      "old_to_new": [
        2,
        3,
        0,
        4,
        5,
        1,
        6,
        7,
        8,
        9,
        10,
        11
      ]
    },
    {
      "elapsed_seconds": 0.4253313750086818,
      "expanded_polynomial_sha256": "d95ba75aa98c1347ca59608f5b0cf02bf6aa3572a4595413b6dac24de5fbb762",
      "msolve": {
        "forward": {
          "output_char_count": 17,
          "output_sha256": "6adf16fd42fd52884a1f6c68aa5f2958952d4026d6d4238b33ddb2fe21e9d75f",
          "returncode": 0,
          "stderr": "",
          "verdict": "NONUNIT"
        },
        "reverse": {
          "output_char_count": 17,
          "output_sha256": "6adf16fd42fd52884a1f6c68aa5f2958952d4026d6d4238b33ddb2fe21e9d75f",
          "returncode": 0,
          "stderr": "",
          "verdict": "NONUNIT"
        }
      },
      "old_anchor_pair": [
        2,
        6
      ],
      "old_to_new": [
        2,
        3,
        0,
        4,
        5,
        6,
        1,
        7,
        8,
        9,
        10,
        11
      ]
    },
    {
      "elapsed_seconds": 0.4261484169983305,
      "expanded_polynomial_sha256": "363e34f8d4fdcef43d8dc22ffca04bccefd850323c4aa66e4aed4dd3222b2e6d",
      "msolve": {
        "forward": {
          "output_char_count": 6,
          "output_sha256": "0333251e6ebb3890ef547f522ec55f27f0cef9a860998757e31f3e1b819e7490",
          "returncode": 0,
          "stderr": "",
          "verdict": "UNIT"
        },
        "reverse": {
          "output_char_count": 6,
          "output_sha256": "0333251e6ebb3890ef547f522ec55f27f0cef9a860998757e31f3e1b819e7490",
          "returncode": 0,
          "stderr": "",
          "verdict": "UNIT"
        }
      },
      "old_anchor_pair": [
        2,
        7
      ],
      "old_to_new": [
        2,
        3,
        0,
        4,
        5,
        6,
        7,
        1,
        8,
        9,
        10,
        11
      ]
    },
    {
      "elapsed_seconds": 0.2805957089876756,
      "expanded_polynomial_sha256": "7e5c942687a7402cf5b24edf8bf709b137b3c6c00ff09d4e27af6444cbd28c03",
      "msolve": {
        "forward": {
          "output_char_count": 17,
          "output_sha256": "6adf16fd42fd52884a1f6c68aa5f2958952d4026d6d4238b33ddb2fe21e9d75f",
          "returncode": 0,
          "stderr": "",
          "verdict": "NONUNIT"
        },
        "reverse": {
          "output_char_count": 17,
          "output_sha256": "6adf16fd42fd52884a1f6c68aa5f2958952d4026d6d4238b33ddb2fe21e9d75f",
          "returncode": 0,
          "stderr": "",
          "verdict": "NONUNIT"
        }
      },
      "old_anchor_pair": [
        2,
        8
      ],
      "old_to_new": [
        2,
        3,
        0,
        4,
        5,
        6,
        7,
        8,
        1,
        9,
        10,
        11
      ]
    },
    {
      "elapsed_seconds": 0.12771675002295524,
      "expanded_polynomial_sha256": "b313ea88dde9c54cf4deee95e01c67c492c5cda37bd2bcb241cd9737793dd9e5",
      "msolve": {
        "forward": {
          "output_char_count": 17,
          "output_sha256": "6adf16fd42fd52884a1f6c68aa5f2958952d4026d6d4238b33ddb2fe21e9d75f",
          "returncode": 0,
          "stderr": "",
          "verdict": "NONUNIT"
        },
        "reverse": {
          "output_char_count": 17,
          "output_sha256": "6adf16fd42fd52884a1f6c68aa5f2958952d4026d6d4238b33ddb2fe21e9d75f",
          "returncode": 0,
          "stderr": "",
          "verdict": "NONUNIT"
        }
      },
      "old_anchor_pair": [
        2,
        9
      ],
      "old_to_new": [
        2,
        3,
        0,
        4,
        5,
        6,
        7,
        8,
        9,
        1,
        10,
        11
      ]
    },
    {
      "elapsed_seconds": 0.29376145801506937,
      "expanded_polynomial_sha256": "b091f76c2944a939a46ef22eabc878371124c94c04fc68ca323d997f8de2e33c",
      "msolve": {
        "forward": {
          "output_char_count": 17,
          "output_sha256": "6adf16fd42fd52884a1f6c68aa5f2958952d4026d6d4238b33ddb2fe21e9d75f",
          "returncode": 0,
          "stderr": "",
          "verdict": "NONUNIT"
        },
        "reverse": {
          "output_char_count": 17,
          "output_sha256": "6adf16fd42fd52884a1f6c68aa5f2958952d4026d6d4238b33ddb2fe21e9d75f",
          "returncode": 0,
          "stderr": "",
          "verdict": "NONUNIT"
        }
      },
      "old_anchor_pair": [
        2,
        10
      ],
      "old_to_new": [
        2,
        3,
        0,
        4,
        5,
        6,
        7,
        8,
        9,
        10,
        1,
        11
      ]
    },
    {
      "elapsed_seconds": 0.33710162501665764,
      "expanded_polynomial_sha256": "47a4f5e16db8d453772fe933bf1eeac16154791f7287e08b2c1c151878582b0f",
      "msolve": {
        "forward": {
          "output_char_count": 17,
          "output_sha256": "6adf16fd42fd52884a1f6c68aa5f2958952d4026d6d4238b33ddb2fe21e9d75f",
          "returncode": 0,
          "stderr": "",
          "verdict": "NONUNIT"
        },
        "reverse": {
          "output_char_count": 17,
          "output_sha256": "6adf16fd42fd52884a1f6c68aa5f2958952d4026d6d4238b33ddb2fe21e9d75f",
          "returncode": 0,
          "stderr": "",
          "verdict": "NONUNIT"
        }
      },
      "old_anchor_pair": [
        2,
        11
      ],
      "old_to_new": [
        2,
        3,
        0,
        4,
        5,
        6,
        7,
        8,
        9,
        10,
        11,
        1
      ]
    },
    {
      "elapsed_seconds": 0.10894049998023547,
      "expanded_polynomial_sha256": "91b5f11c62182078a33e6fdc4f89ec9cccc31be8617ac42017d38c3431ac9967",
      "msolve": {
        "forward": {
          "output_char_count": 6,
          "output_sha256": "0333251e6ebb3890ef547f522ec55f27f0cef9a860998757e31f3e1b819e7490",
          "returncode": 0,
          "stderr": "",
          "verdict": "UNIT"
        },
        "reverse": {
          "output_char_count": 6,
          "output_sha256": "0333251e6ebb3890ef547f522ec55f27f0cef9a860998757e31f3e1b819e7490",
          "returncode": 0,
          "stderr": "",
          "verdict": "UNIT"
        }
      },
      "old_anchor_pair": [
        3,
        4
      ],
      "old_to_new": [
        2,
        3,
        4,
        0,
        1,
        5,
        6,
        7,
        8,
        9,
        10,
        11
      ]
    },
    {
      "elapsed_seconds": 0.12095429198234342,
      "expanded_polynomial_sha256": "ed35157310c7d6e7e741cdc394e2210db5aa5ac5618192ca616142ab03e01bc3",
      "msolve": {
        "forward": {
          "output_char_count": 6,
          "output_sha256": "0333251e6ebb3890ef547f522ec55f27f0cef9a860998757e31f3e1b819e7490",
          "returncode": 0,
          "stderr": "",
          "verdict": "UNIT"
        },
        "reverse": {
          "output_char_count": 6,
          "output_sha256": "0333251e6ebb3890ef547f522ec55f27f0cef9a860998757e31f3e1b819e7490",
          "returncode": 0,
          "stderr": "",
          "verdict": "UNIT"
        }
      },
      "old_anchor_pair": [
        3,
        5
      ],
      "old_to_new": [
        2,
        3,
        4,
        0,
        5,
        1,
        6,
        7,
        8,
        9,
        10,
        11
      ]
    },
    {
      "elapsed_seconds": 0.04453162499703467,
      "expanded_polynomial_sha256": "2678fc2d652273dff99409045c23003ac1c178ddf3bba4a9292ed3785f7948fc",
      "msolve": {
        "forward": {
          "output_char_count": 17,
          "output_sha256": "6adf16fd42fd52884a1f6c68aa5f2958952d4026d6d4238b33ddb2fe21e9d75f",
          "returncode": 0,
          "stderr": "",
          "verdict": "NONUNIT"
        },
        "reverse": {
          "output_char_count": 17,
          "output_sha256": "6adf16fd42fd52884a1f6c68aa5f2958952d4026d6d4238b33ddb2fe21e9d75f",
          "returncode": 0,
          "stderr": "",
          "verdict": "NONUNIT"
        }
      },
      "old_anchor_pair": [
        3,
        6
      ],
      "old_to_new": [
        2,
        3,
        4,
        0,
        5,
        6,
        1,
        7,
        8,
        9,
        10,
        11
      ]
    },
    {
      "elapsed_seconds": 0.4665375830081757,
      "expanded_polynomial_sha256": "3a870ce339f8067862d5dcaf07eb08bb2d8afb22d46b73296975cd5717d821e2",
      "msolve": {
        "forward": {
          "output_char_count": 17,
          "output_sha256": "6adf16fd42fd52884a1f6c68aa5f2958952d4026d6d4238b33ddb2fe21e9d75f",
          "returncode": 0,
          "stderr": "",
          "verdict": "NONUNIT"
        },
        "reverse": {
          "output_char_count": 17,
          "output_sha256": "6adf16fd42fd52884a1f6c68aa5f2958952d4026d6d4238b33ddb2fe21e9d75f",
          "returncode": 0,
          "stderr": "",
          "verdict": "NONUNIT"
        }
      },
      "old_anchor_pair": [
        3,
        7
      ],
      "old_to_new": [
        2,
        3,
        4,
        0,
        5,
        6,
        7,
        1,
        8,
        9,
        10,
        11
      ]
    },
    {
      "elapsed_seconds": 0.24312454200116917,
      "expanded_polynomial_sha256": "1b510222145cf8d3a1a3f47fe5d31ed38eb77ce9e92b02a029a3d9a571dd0534",
      "msolve": {
        "forward": {
          "output_char_count": 17,
          "output_sha256": "6adf16fd42fd52884a1f6c68aa5f2958952d4026d6d4238b33ddb2fe21e9d75f",
          "returncode": 0,
          "stderr": "",
          "verdict": "NONUNIT"
        },
        "reverse": {
          "output_char_count": 17,
          "output_sha256": "6adf16fd42fd52884a1f6c68aa5f2958952d4026d6d4238b33ddb2fe21e9d75f",
          "returncode": 0,
          "stderr": "",
          "verdict": "NONUNIT"
        }
      },
      "old_anchor_pair": [
        3,
        8
      ],
      "old_to_new": [
        2,
        3,
        4,
        0,
        5,
        6,
        7,
        8,
        1,
        9,
        10,
        11
      ]
    },
    {
      "elapsed_seconds": 0.5292691250215285,
      "expanded_polynomial_sha256": "f41c717f01eea860fc76928f0dbaf5559f6d0683bc4c87bdec58bf1a18d46cea",
      "msolve": {
        "forward": {
          "output_char_count": 6,
          "output_sha256": "0333251e6ebb3890ef547f522ec55f27f0cef9a860998757e31f3e1b819e7490",
          "returncode": 0,
          "stderr": "",
          "verdict": "UNIT"
        },
        "reverse": {
          "output_char_count": 6,
          "output_sha256": "0333251e6ebb3890ef547f522ec55f27f0cef9a860998757e31f3e1b819e7490",
          "returncode": 0,
          "stderr": "",
          "verdict": "UNIT"
        }
      },
      "old_anchor_pair": [
        3,
        9
      ],
      "old_to_new": [
        2,
        3,
        4,
        0,
        5,
        6,
        7,
        8,
        9,
        1,
        10,
        11
      ]
    },
    {
      "elapsed_seconds": 0.33506237500114366,
      "expanded_polynomial_sha256": "d7822c0a08b95a52567ba2650275a5bd74391aed8c8bb55c56472ac585ee8618",
      "msolve": {
        "forward": {
          "output_char_count": 17,
          "output_sha256": "6adf16fd42fd52884a1f6c68aa5f2958952d4026d6d4238b33ddb2fe21e9d75f",
          "returncode": 0,
          "stderr": "",
          "verdict": "NONUNIT"
        },
        "reverse": {
          "output_char_count": 17,
          "output_sha256": "6adf16fd42fd52884a1f6c68aa5f2958952d4026d6d4238b33ddb2fe21e9d75f",
          "returncode": 0,
          "stderr": "",
          "verdict": "NONUNIT"
        }
      },
      "old_anchor_pair": [
        3,
        10
      ],
      "old_to_new": [
        2,
        3,
        4,
        0,
        5,
        6,
        7,
        8,
        9,
        10,
        1,
        11
      ]
    },
    {
      "elapsed_seconds": 0.11344704200746492,
      "expanded_polynomial_sha256": "b45b03a5a77a98d6363580a1d0a4c94ca4cfc6b6bd089a90217b5a287474c16f",
      "msolve": {
        "forward": {
          "output_char_count": 6,
          "output_sha256": "0333251e6ebb3890ef547f522ec55f27f0cef9a860998757e31f3e1b819e7490",
          "returncode": 0,
          "stderr": "",
          "verdict": "UNIT"
        },
        "reverse": {
          "output_char_count": 6,
          "output_sha256": "0333251e6ebb3890ef547f522ec55f27f0cef9a860998757e31f3e1b819e7490",
          "returncode": 0,
          "stderr": "",
          "verdict": "UNIT"
        }
      },
      "old_anchor_pair": [
        3,
        11
      ],
      "old_to_new": [
        2,
        3,
        4,
        0,
        5,
        6,
        7,
        8,
        9,
        10,
        11,
        1
      ]
    },
    {
      "elapsed_seconds": 0.1070194170169998,
      "expanded_polynomial_sha256": "045f255418dcf0c51f862ca209c5e0b46f8ec13ddabf9c606bd5c3d94a513e8d",
      "msolve": {
        "forward": {
          "output_char_count": 6,
          "output_sha256": "0333251e6ebb3890ef547f522ec55f27f0cef9a860998757e31f3e1b819e7490",
          "returncode": 0,
          "stderr": "",
          "verdict": "UNIT"
        },
        "reverse": {
          "output_char_count": 6,
          "output_sha256": "0333251e6ebb3890ef547f522ec55f27f0cef9a860998757e31f3e1b819e7490",
          "returncode": 0,
          "stderr": "",
          "verdict": "UNIT"
        }
      },
      "old_anchor_pair": [
        4,
        5
      ],
      "old_to_new": [
        2,
        3,
        4,
        5,
        0,
        1,
        6,
        7,
        8,
        9,
        10,
        11
      ]
    },
    {
      "elapsed_seconds": 0.09705612499965355,
      "expanded_polynomial_sha256": "a716b729183edb49f82c402b2f5f94c3df0572ced3e059d53f0e641f873945a1",
      "msolve": {
        "forward": {
          "output_char_count": 6,
          "output_sha256": "0333251e6ebb3890ef547f522ec55f27f0cef9a860998757e31f3e1b819e7490",
          "returncode": 0,
          "stderr": "",
          "verdict": "UNIT"
        },
        "reverse": {
          "output_char_count": 6,
          "output_sha256": "0333251e6ebb3890ef547f522ec55f27f0cef9a860998757e31f3e1b819e7490",
          "returncode": 0,
          "stderr": "",
          "verdict": "UNIT"
        }
      },
      "old_anchor_pair": [
        4,
        6
      ],
      "old_to_new": [
        2,
        3,
        4,
        5,
        0,
        6,
        1,
        7,
        8,
        9,
        10,
        11
      ]
    },
    {
      "elapsed_seconds": 0.22517358302138746,
      "expanded_polynomial_sha256": "00534b4a692f3bf80ef24993699e2778fba7108748b823443d17c262fc263670",
      "msolve": {
        "forward": {
          "output_char_count": 17,
          "output_sha256": "6adf16fd42fd52884a1f6c68aa5f2958952d4026d6d4238b33ddb2fe21e9d75f",
          "returncode": 0,
          "stderr": "",
          "verdict": "NONUNIT"
        },
        "reverse": {
          "output_char_count": 17,
          "output_sha256": "6adf16fd42fd52884a1f6c68aa5f2958952d4026d6d4238b33ddb2fe21e9d75f",
          "returncode": 0,
          "stderr": "",
          "verdict": "NONUNIT"
        }
      },
      "old_anchor_pair": [
        4,
        7
      ],
      "old_to_new": [
        2,
        3,
        4,
        5,
        0,
        6,
        7,
        1,
        8,
        9,
        10,
        11
      ]
    },
    {
      "elapsed_seconds": 0.2633097079815343,
      "expanded_polynomial_sha256": "39d127fda3eacf587d17bc71d3e1ea5f693012cab2472e58a1b2f02238aec7f8",
      "msolve": {
        "forward": {
          "output_char_count": 17,
          "output_sha256": "6adf16fd42fd52884a1f6c68aa5f2958952d4026d6d4238b33ddb2fe21e9d75f",
          "returncode": 0,
          "stderr": "",
          "verdict": "NONUNIT"
        },
        "reverse": {
          "output_char_count": 17,
          "output_sha256": "6adf16fd42fd52884a1f6c68aa5f2958952d4026d6d4238b33ddb2fe21e9d75f",
          "returncode": 0,
          "stderr": "",
          "verdict": "NONUNIT"
        }
      },
      "old_anchor_pair": [
        4,
        8
      ],
      "old_to_new": [
        2,
        3,
        4,
        5,
        0,
        6,
        7,
        8,
        1,
        9,
        10,
        11
      ]
    },
    {
      "elapsed_seconds": 0.3136288750101812,
      "expanded_polynomial_sha256": "aabc49e0cd9ab2209ca25935ad046daa2a05df01c3ad0e082d943df42487ce5a",
      "msolve": {
        "forward": {
          "output_char_count": 17,
          "output_sha256": "6adf16fd42fd52884a1f6c68aa5f2958952d4026d6d4238b33ddb2fe21e9d75f",
          "returncode": 0,
          "stderr": "",
          "verdict": "NONUNIT"
        },
        "reverse": {
          "output_char_count": 17,
          "output_sha256": "6adf16fd42fd52884a1f6c68aa5f2958952d4026d6d4238b33ddb2fe21e9d75f",
          "returncode": 0,
          "stderr": "",
          "verdict": "NONUNIT"
        }
      },
      "old_anchor_pair": [
        4,
        9
      ],
      "old_to_new": [
        2,
        3,
        4,
        5,
        0,
        6,
        7,
        8,
        9,
        1,
        10,
        11
      ]
    },
    {
      "elapsed_seconds": 0.349055041995598,
      "expanded_polynomial_sha256": "341a18ddde57d770d815160d035d7cf8c7bd5eb21ad45627dd354780d4b6ab72",
      "msolve": {
        "forward": {
          "output_char_count": 17,
          "output_sha256": "6adf16fd42fd52884a1f6c68aa5f2958952d4026d6d4238b33ddb2fe21e9d75f",
          "returncode": 0,
          "stderr": "",
          "verdict": "NONUNIT"
        },
        "reverse": {
          "output_char_count": 17,
          "output_sha256": "6adf16fd42fd52884a1f6c68aa5f2958952d4026d6d4238b33ddb2fe21e9d75f",
          "returncode": 0,
          "stderr": "",
          "verdict": "NONUNIT"
        }
      },
      "old_anchor_pair": [
        4,
        10
      ],
      "old_to_new": [
        2,
        3,
        4,
        5,
        0,
        6,
        7,
        8,
        9,
        10,
        1,
        11
      ]
    },
    {
      "elapsed_seconds": 0.11609779199352488,
      "expanded_polynomial_sha256": "5edca5c0a8f7ad70b349b6cdea2fa737fe68c98f3f62de962215cf398aaaaade",
      "msolve": {
        "forward": {
          "output_char_count": 6,
          "output_sha256": "0333251e6ebb3890ef547f522ec55f27f0cef9a860998757e31f3e1b819e7490",
          "returncode": 0,
          "stderr": "",
          "verdict": "UNIT"
        },
        "reverse": {
          "output_char_count": 6,
          "output_sha256": "0333251e6ebb3890ef547f522ec55f27f0cef9a860998757e31f3e1b819e7490",
          "returncode": 0,
          "stderr": "",
          "verdict": "UNIT"
        }
      },
      "old_anchor_pair": [
        4,
        11
      ],
      "old_to_new": [
        2,
        3,
        4,
        5,
        0,
        6,
        7,
        8,
        9,
        10,
        11,
        1
      ]
    },
    {
      "elapsed_seconds": 0.08163454200257547,
      "expanded_polynomial_sha256": "45ab297600f422129efc978a32a34001983dc9b409093ec770a07af9267b99d6",
      "msolve": {
        "forward": {
          "output_char_count": 6,
          "output_sha256": "0333251e6ebb3890ef547f522ec55f27f0cef9a860998757e31f3e1b819e7490",
          "returncode": 0,
          "stderr": "",
          "verdict": "UNIT"
        },
        "reverse": {
          "output_char_count": 6,
          "output_sha256": "0333251e6ebb3890ef547f522ec55f27f0cef9a860998757e31f3e1b819e7490",
          "returncode": 0,
          "stderr": "",
          "verdict": "UNIT"
        }
      },
      "old_anchor_pair": [
        5,
        6
      ],
      "old_to_new": [
        2,
        3,
        4,
        5,
        6,
        0,
        1,
        7,
        8,
        9,
        10,
        11
      ]
    },
    {
      "elapsed_seconds": 0.49940883298404515,
      "expanded_polynomial_sha256": "43a67ba29e7a3a2e4fc5ba3cfb0c964e334cbb2adec461963ab22fe85bacf47a",
      "msolve": {
        "forward": {
          "output_char_count": 17,
          "output_sha256": "6adf16fd42fd52884a1f6c68aa5f2958952d4026d6d4238b33ddb2fe21e9d75f",
          "returncode": 0,
          "stderr": "",
          "verdict": "NONUNIT"
        },
        "reverse": {
          "output_char_count": 17,
          "output_sha256": "6adf16fd42fd52884a1f6c68aa5f2958952d4026d6d4238b33ddb2fe21e9d75f",
          "returncode": 0,
          "stderr": "",
          "verdict": "NONUNIT"
        }
      },
      "old_anchor_pair": [
        5,
        7
      ],
      "old_to_new": [
        2,
        3,
        4,
        5,
        6,
        0,
        7,
        1,
        8,
        9,
        10,
        11
      ]
    },
    {
      "elapsed_seconds": 0.4428737080015708,
      "expanded_polynomial_sha256": "c7f954112f3f7cb8df37292259e2268f4ffc9db1353ff815498aa6d8cf72d13d",
      "msolve": {
        "forward": {
          "output_char_count": 17,
          "output_sha256": "6adf16fd42fd52884a1f6c68aa5f2958952d4026d6d4238b33ddb2fe21e9d75f",
          "returncode": 0,
          "stderr": "",
          "verdict": "NONUNIT"
        },
        "reverse": {
          "output_char_count": 17,
          "output_sha256": "6adf16fd42fd52884a1f6c68aa5f2958952d4026d6d4238b33ddb2fe21e9d75f",
          "returncode": 0,
          "stderr": "",
          "verdict": "NONUNIT"
        }
      },
      "old_anchor_pair": [
        5,
        8
      ],
      "old_to_new": [
        2,
        3,
        4,
        5,
        6,
        0,
        7,
        8,
        1,
        9,
        10,
        11
      ]
    },
    {
      "elapsed_seconds": 0.3687620410055388,
      "expanded_polynomial_sha256": "e7ea33278d0a3f4af59e17a155db01e6fe00dc159bb05bc639ec38f5cac00a75",
      "msolve": {
        "forward": {
          "output_char_count": 17,
          "output_sha256": "6adf16fd42fd52884a1f6c68aa5f2958952d4026d6d4238b33ddb2fe21e9d75f",
          "returncode": 0,
          "stderr": "",
          "verdict": "NONUNIT"
        },
        "reverse": {
          "output_char_count": 17,
          "output_sha256": "6adf16fd42fd52884a1f6c68aa5f2958952d4026d6d4238b33ddb2fe21e9d75f",
          "returncode": 0,
          "stderr": "",
          "verdict": "NONUNIT"
        }
      },
      "old_anchor_pair": [
        5,
        9
      ],
      "old_to_new": [
        2,
        3,
        4,
        5,
        6,
        0,
        7,
        8,
        9,
        1,
        10,
        11
      ]
    },
    {
      "elapsed_seconds": 0.3992748750024475,
      "expanded_polynomial_sha256": "7837f4adf17497dcbc3645c6e31fc4c7d503b5c247955c0242895c109f0f9663",
      "msolve": {
        "forward": {
          "output_char_count": 6,
          "output_sha256": "0333251e6ebb3890ef547f522ec55f27f0cef9a860998757e31f3e1b819e7490",
          "returncode": 0,
          "stderr": "",
          "verdict": "UNIT"
        },
        "reverse": {
          "output_char_count": 6,
          "output_sha256": "0333251e6ebb3890ef547f522ec55f27f0cef9a860998757e31f3e1b819e7490",
          "returncode": 0,
          "stderr": "",
          "verdict": "UNIT"
        }
      },
      "old_anchor_pair": [
        5,
        10
      ],
      "old_to_new": [
        2,
        3,
        4,
        5,
        6,
        0,
        7,
        8,
        9,
        10,
        1,
        11
      ]
    },
    {
      "elapsed_seconds": 0.09607695799786597,
      "expanded_polynomial_sha256": "8270f6e52a7154a36a110a3e0b571cde894b19b3d059a86a721e8e71b072d66a",
      "msolve": {
        "forward": {
          "output_char_count": 17,
          "output_sha256": "6adf16fd42fd52884a1f6c68aa5f2958952d4026d6d4238b33ddb2fe21e9d75f",
          "returncode": 0,
          "stderr": "",
          "verdict": "NONUNIT"
        },
        "reverse": {
          "output_char_count": 17,
          "output_sha256": "6adf16fd42fd52884a1f6c68aa5f2958952d4026d6d4238b33ddb2fe21e9d75f",
          "returncode": 0,
          "stderr": "",
          "verdict": "NONUNIT"
        }
      },
      "old_anchor_pair": [
        5,
        11
      ],
      "old_to_new": [
        2,
        3,
        4,
        5,
        6,
        0,
        7,
        8,
        9,
        10,
        11,
        1
      ]
    },
    {
      "elapsed_seconds": 0.39425954199396074,
      "expanded_polynomial_sha256": "032826fd9deb381f64a35bdf4eae72835e673d94652976afe8b72ba1c2047ba0",
      "msolve": {
        "forward": {
          "output_char_count": 6,
          "output_sha256": "0333251e6ebb3890ef547f522ec55f27f0cef9a860998757e31f3e1b819e7490",
          "returncode": 0,
          "stderr": "",
          "verdict": "UNIT"
        },
        "reverse": {
          "output_char_count": 6,
          "output_sha256": "0333251e6ebb3890ef547f522ec55f27f0cef9a860998757e31f3e1b819e7490",
          "returncode": 0,
          "stderr": "",
          "verdict": "UNIT"
        }
      },
      "old_anchor_pair": [
        6,
        7
      ],
      "old_to_new": [
        2,
        3,
        4,
        5,
        6,
        7,
        0,
        1,
        8,
        9,
        10,
        11
      ]
    },
    {
      "elapsed_seconds": 0.3586258750001434,
      "expanded_polynomial_sha256": "8632ec4744745b82c2699ea2aae7e708e05d7fb55f52471e518420f5897763df",
      "msolve": {
        "forward": {
          "output_char_count": 17,
          "output_sha256": "6adf16fd42fd52884a1f6c68aa5f2958952d4026d6d4238b33ddb2fe21e9d75f",
          "returncode": 0,
          "stderr": "",
          "verdict": "NONUNIT"
        },
        "reverse": {
          "output_char_count": 17,
          "output_sha256": "6adf16fd42fd52884a1f6c68aa5f2958952d4026d6d4238b33ddb2fe21e9d75f",
          "returncode": 0,
          "stderr": "",
          "verdict": "NONUNIT"
        }
      },
      "old_anchor_pair": [
        6,
        8
      ],
      "old_to_new": [
        2,
        3,
        4,
        5,
        6,
        7,
        0,
        8,
        1,
        9,
        10,
        11
      ]
    },
    {
      "elapsed_seconds": 0.327116833999753,
      "expanded_polynomial_sha256": "dce4a4f9eae414e2b601ba9d097938c7eec1e6ef3f99965e6017c43e39ae82df",
      "msolve": {
        "forward": {
          "output_char_count": 17,
          "output_sha256": "6adf16fd42fd52884a1f6c68aa5f2958952d4026d6d4238b33ddb2fe21e9d75f",
          "returncode": 0,
          "stderr": "",
          "verdict": "NONUNIT"
        },
        "reverse": {
          "output_char_count": 17,
          "output_sha256": "6adf16fd42fd52884a1f6c68aa5f2958952d4026d6d4238b33ddb2fe21e9d75f",
          "returncode": 0,
          "stderr": "",
          "verdict": "NONUNIT"
        }
      },
      "old_anchor_pair": [
        6,
        9
      ],
      "old_to_new": [
        2,
        3,
        4,
        5,
        6,
        7,
        0,
        8,
        9,
        1,
        10,
        11
      ]
    },
    {
      "elapsed_seconds": 0.4800558339920826,
      "expanded_polynomial_sha256": "33f2b7f4ce53e32fcb9514cc1f86bf6054b4542b869999de48802e7be87c5187",
      "msolve": {
        "forward": {
          "output_char_count": 17,
          "output_sha256": "6adf16fd42fd52884a1f6c68aa5f2958952d4026d6d4238b33ddb2fe21e9d75f",
          "returncode": 0,
          "stderr": "",
          "verdict": "NONUNIT"
        },
        "reverse": {
          "output_char_count": 17,
          "output_sha256": "6adf16fd42fd52884a1f6c68aa5f2958952d4026d6d4238b33ddb2fe21e9d75f",
          "returncode": 0,
          "stderr": "",
          "verdict": "NONUNIT"
        }
      },
      "old_anchor_pair": [
        6,
        10
      ],
      "old_to_new": [
        2,
        3,
        4,
        5,
        6,
        7,
        0,
        8,
        9,
        10,
        1,
        11
      ]
    },
    {
      "elapsed_seconds": 0.28149241700884886,
      "expanded_polynomial_sha256": "63cb6286f0428bd51a9e9e0f6d8fe0aae22b763f86a091ca4ca7349dafdcfef7",
      "msolve": {
        "forward": {
          "output_char_count": 17,
          "output_sha256": "6adf16fd42fd52884a1f6c68aa5f2958952d4026d6d4238b33ddb2fe21e9d75f",
          "returncode": 0,
          "stderr": "",
          "verdict": "NONUNIT"
        },
        "reverse": {
          "output_char_count": 17,
          "output_sha256": "6adf16fd42fd52884a1f6c68aa5f2958952d4026d6d4238b33ddb2fe21e9d75f",
          "returncode": 0,
          "stderr": "",
          "verdict": "NONUNIT"
        }
      },
      "old_anchor_pair": [
        6,
        11
      ],
      "old_to_new": [
        2,
        3,
        4,
        5,
        6,
        7,
        0,
        8,
        9,
        10,
        11,
        1
      ]
    },
    {
      "elapsed_seconds": 0.40183049999177456,
      "expanded_polynomial_sha256": "812777808d103e0f0213da95c55f5f7b927c6ddb821ec57b2ba2152e3c25632c",
      "msolve": {
        "forward": {
          "output_char_count": 6,
          "output_sha256": "0333251e6ebb3890ef547f522ec55f27f0cef9a860998757e31f3e1b819e7490",
          "returncode": 0,
          "stderr": "",
          "verdict": "UNIT"
        },
        "reverse": {
          "output_char_count": 6,
          "output_sha256": "0333251e6ebb3890ef547f522ec55f27f0cef9a860998757e31f3e1b819e7490",
          "returncode": 0,
          "stderr": "",
          "verdict": "UNIT"
        }
      },
      "old_anchor_pair": [
        7,
        8
      ],
      "old_to_new": [
        2,
        3,
        4,
        5,
        6,
        7,
        8,
        0,
        1,
        9,
        10,
        11
      ]
    },
    {
      "elapsed_seconds": 0.43397358400397934,
      "expanded_polynomial_sha256": "3e49619dc7cdc2eeffc71dad633addd25301c356ef465909bb87a0e5d383206e",
      "msolve": {
        "forward": {
          "output_char_count": 17,
          "output_sha256": "6adf16fd42fd52884a1f6c68aa5f2958952d4026d6d4238b33ddb2fe21e9d75f",
          "returncode": 0,
          "stderr": "",
          "verdict": "NONUNIT"
        },
        "reverse": {
          "output_char_count": 17,
          "output_sha256": "6adf16fd42fd52884a1f6c68aa5f2958952d4026d6d4238b33ddb2fe21e9d75f",
          "returncode": 0,
          "stderr": "",
          "verdict": "NONUNIT"
        }
      },
      "old_anchor_pair": [
        7,
        9
      ],
      "old_to_new": [
        2,
        3,
        4,
        5,
        6,
        7,
        8,
        0,
        9,
        1,
        10,
        11
      ]
    },
    {
      "elapsed_seconds": 0.31107737502316013,
      "expanded_polynomial_sha256": "d57ae4c66a6a191f81d8d8e476f0583136c9f5272b319942190d182e693d726a",
      "msolve": {
        "forward": {
          "output_char_count": 17,
          "output_sha256": "6adf16fd42fd52884a1f6c68aa5f2958952d4026d6d4238b33ddb2fe21e9d75f",
          "returncode": 0,
          "stderr": "",
          "verdict": "NONUNIT"
        },
        "reverse": {
          "output_char_count": 17,
          "output_sha256": "6adf16fd42fd52884a1f6c68aa5f2958952d4026d6d4238b33ddb2fe21e9d75f",
          "returncode": 0,
          "stderr": "",
          "verdict": "NONUNIT"
        }
      },
      "old_anchor_pair": [
        7,
        10
      ],
      "old_to_new": [
        2,
        3,
        4,
        5,
        6,
        7,
        8,
        0,
        9,
        10,
        1,
        11
      ]
    },
    {
      "elapsed_seconds": 0.34170625000842847,
      "expanded_polynomial_sha256": "2503b3ff494359d177c23b8fc76b869bbd06b1a97208cdbfaa089749b122fb25",
      "msolve": {
        "forward": {
          "output_char_count": 6,
          "output_sha256": "0333251e6ebb3890ef547f522ec55f27f0cef9a860998757e31f3e1b819e7490",
          "returncode": 0,
          "stderr": "",
          "verdict": "UNIT"
        },
        "reverse": {
          "output_char_count": 6,
          "output_sha256": "0333251e6ebb3890ef547f522ec55f27f0cef9a860998757e31f3e1b819e7490",
          "returncode": 0,
          "stderr": "",
          "verdict": "UNIT"
        }
      },
      "old_anchor_pair": [
        7,
        11
      ],
      "old_to_new": [
        2,
        3,
        4,
        5,
        6,
        7,
        8,
        0,
        9,
        10,
        11,
        1
      ]
    },
    {
      "elapsed_seconds": 0.4991346249880735,
      "expanded_polynomial_sha256": "6551caafef924c1674e608be161eec634ce26eed435bdb021881e6a3d0f1c059",
      "msolve": {
        "forward": {
          "output_char_count": 17,
          "output_sha256": "6adf16fd42fd52884a1f6c68aa5f2958952d4026d6d4238b33ddb2fe21e9d75f",
          "returncode": 0,
          "stderr": "",
          "verdict": "NONUNIT"
        },
        "reverse": {
          "output_char_count": 17,
          "output_sha256": "6adf16fd42fd52884a1f6c68aa5f2958952d4026d6d4238b33ddb2fe21e9d75f",
          "returncode": 0,
          "stderr": "",
          "verdict": "NONUNIT"
        }
      },
      "old_anchor_pair": [
        8,
        9
      ],
      "old_to_new": [
        2,
        3,
        4,
        5,
        6,
        7,
        8,
        9,
        0,
        1,
        10,
        11
      ]
    },
    {
      "elapsed_seconds": 0.3718985829909798,
      "expanded_polynomial_sha256": "e7afd4c456320a496d1c91d241b82663cde63959155beb2dece0d2ffe616308b",
      "msolve": {
        "forward": {
          "output_char_count": 17,
          "output_sha256": "6adf16fd42fd52884a1f6c68aa5f2958952d4026d6d4238b33ddb2fe21e9d75f",
          "returncode": 0,
          "stderr": "",
          "verdict": "NONUNIT"
        },
        "reverse": {
          "output_char_count": 17,
          "output_sha256": "6adf16fd42fd52884a1f6c68aa5f2958952d4026d6d4238b33ddb2fe21e9d75f",
          "returncode": 0,
          "stderr": "",
          "verdict": "NONUNIT"
        }
      },
      "old_anchor_pair": [
        8,
        10
      ],
      "old_to_new": [
        2,
        3,
        4,
        5,
        6,
        7,
        8,
        9,
        0,
        10,
        1,
        11
      ]
    },
    {
      "elapsed_seconds": 0.24051458298345096,
      "expanded_polynomial_sha256": "a350ce4717a903f3286eea96704b83c6c07ec917294f76d8cb7679548b18ad21",
      "msolve": {
        "forward": {
          "output_char_count": 17,
          "output_sha256": "6adf16fd42fd52884a1f6c68aa5f2958952d4026d6d4238b33ddb2fe21e9d75f",
          "returncode": 0,
          "stderr": "",
          "verdict": "NONUNIT"
        },
        "reverse": {
          "output_char_count": 17,
          "output_sha256": "6adf16fd42fd52884a1f6c68aa5f2958952d4026d6d4238b33ddb2fe21e9d75f",
          "returncode": 0,
          "stderr": "",
          "verdict": "NONUNIT"
        }
      },
      "old_anchor_pair": [
        8,
        11
      ],
      "old_to_new": [
        2,
        3,
        4,
        5,
        6,
        7,
        8,
        9,
        0,
        10,
        11,
        1
      ]
    },
    {
      "elapsed_seconds": 0.34432425000704825,
      "expanded_polynomial_sha256": "5cc7f576d3e015e14e9e8329b1b430d1fa6159277de6631a2dc09ae6c3281f39",
      "msolve": {
        "forward": {
          "output_char_count": 17,
          "output_sha256": "6adf16fd42fd52884a1f6c68aa5f2958952d4026d6d4238b33ddb2fe21e9d75f",
          "returncode": 0,
          "stderr": "",
          "verdict": "NONUNIT"
        },
        "reverse": {
          "output_char_count": 17,
          "output_sha256": "6adf16fd42fd52884a1f6c68aa5f2958952d4026d6d4238b33ddb2fe21e9d75f",
          "returncode": 0,
          "stderr": "",
          "verdict": "NONUNIT"
        }
      },
      "old_anchor_pair": [
        9,
        10
      ],
      "old_to_new": [
        2,
        3,
        4,
        5,
        6,
        7,
        8,
        9,
        10,
        0,
        1,
        11
      ]
    },
    {
      "elapsed_seconds": 0.3142702090262901,
      "expanded_polynomial_sha256": "096c2201fb2c6b987faad6aeef83e31bdbf1c3f40a1ab6d629874c3063db3662",
      "msolve": {
        "forward": {
          "output_char_count": 17,
          "output_sha256": "6adf16fd42fd52884a1f6c68aa5f2958952d4026d6d4238b33ddb2fe21e9d75f",
          "returncode": 0,
          "stderr": "",
          "verdict": "NONUNIT"
        },
        "reverse": {
          "output_char_count": 17,
          "output_sha256": "6adf16fd42fd52884a1f6c68aa5f2958952d4026d6d4238b33ddb2fe21e9d75f",
          "returncode": 0,
          "stderr": "",
          "verdict": "NONUNIT"
        }
      },
      "old_anchor_pair": [
        9,
        11
      ],
      "old_to_new": [
        2,
        3,
        4,
        5,
        6,
        7,
        8,
        9,
        10,
        0,
        11,
        1
      ]
    },
    {
      "elapsed_seconds": 0.5062640830001328,
      "expanded_polynomial_sha256": "ae3a795d961471bdb749fcac983c64ad47f0042fe0e59b58d1085c280838679d",
      "msolve": {
        "forward": {
          "output_char_count": 17,
          "output_sha256": "6adf16fd42fd52884a1f6c68aa5f2958952d4026d6d4238b33ddb2fe21e9d75f",
          "returncode": 0,
          "stderr": "",
          "verdict": "NONUNIT"
        },
        "reverse": {
          "output_char_count": 17,
          "output_sha256": "6adf16fd42fd52884a1f6c68aa5f2958952d4026d6d4238b33ddb2fe21e9d75f",
          "returncode": 0,
          "stderr": "",
          "verdict": "NONUNIT"
        }
      },
      "old_anchor_pair": [
        10,
        11
      ],
      "old_to_new": [
        2,
        3,
        4,
        5,
        6,
        7,
        8,
        9,
        10,
        11,
        0,
        1
      ]
    }
  ],
  "schema": "p97-source-indexed-anchor-pair-gauge-scan-v1",
  "timeout_seconds_per_order": 120.0
}
