{
  "aggregate_status": "ALL_CROSSCHECKED_UNIT_EQUALITY_SUBSYSTEMS",
  "cases": [
    {
      "input_row_deletion_complete": false,
      "input_row_irredundant": false,
      "input_rows": [
        {
          "center": 0,
          "support": [
            1,
            2,
            3,
            4
          ]
        },
        {
          "center": 2,
          "support": [
            0,
            1,
            9,
            10
          ]
        },
        {
          "center": 6,
          "support": [
            3,
            5,
            8,
            10
          ]
        },
        {
          "center": 7,
          "support": [
            4,
            6,
            9,
            11
          ]
        },
        {
          "center": 8,
          "support": [
            0,
            4,
            5,
            7
          ]
        },
        {
          "center": 9,
          "support": [
            2,
            8,
            10,
            11
          ]
        },
        {
          "center": 10,
          "support": [
            0,
            3,
            7,
            11
          ]
        },
        {
          "center": 11,
          "support": [
            0,
            1,
            5,
            6
          ]
        }
      ],
      "input_rows_sha256": "32adf75a0509e5b74206f07aef42b59ec44d2636dc934dd9f231b53a6ac4e128",
      "minimization": {
        "attempt_count": 30,
        "attempts_sha256": "91868d87b6b48db46060c97eb977d8a2f9a744fe1c141de48746fb05edbde211",
        "budget_exhausted": true,
        "completed_passes": 2,
        "final_crosscheck": {
          "msolve_qq_forward_variables": {
            "verdict": "UNIT"
          },
          "msolve_qq_reverse_variables": {
            "verdict": "UNIT"
          },
          "singular_qq": {
            "verdict": "UNIT"
          },
          "status": "CROSSCHECKED_UNIT"
        },
        "initial_crosscheck": {
          "msolve_qq_forward_variables": {
            "verdict": "UNIT"
          },
          "msolve_qq_reverse_variables": {
            "verdict": "UNIT"
          },
          "singular_qq": {
            "verdict": "UNIT"
          },
          "status": "CROSSCHECKED_UNIT"
        },
        "initial_equality_count": 24,
        "retained_equalities": [
          {
            "center": 0,
            "left": 1,
            "right": 2,
            "row_index": 0
          },
          {
            "center": 2,
            "left": 0,
            "right": 1,
            "row_index": 1
          },
          {
            "center": 2,
            "left": 0,
            "right": 9,
            "row_index": 1
          },
          {
            "center": 2,
            "left": 0,
            "right": 10,
            "row_index": 1
          },
          {
            "center": 6,
            "left": 3,
            "right": 5,
            "row_index": 2
          },
          {
            "center": 6,
            "left": 3,
            "right": 8,
            "row_index": 2
          },
          {
            "center": 6,
            "left": 3,
            "right": 10,
            "row_index": 2
          },
          {
            "center": 7,
            "left": 4,
            "right": 6,
            "row_index": 3
          },
          {
            "center": 7,
            "left": 4,
            "right": 9,
            "row_index": 3
          },
          {
            "center": 7,
            "left": 4,
            "right": 11,
            "row_index": 3
          },
          {
            "center": 8,
            "left": 0,
            "right": 5,
            "row_index": 4
          },
          {
            "center": 8,
            "left": 0,
            "right": 7,
            "row_index": 4
          },
          {
            "center": 9,
            "left": 2,
            "right": 8,
            "row_index": 5
          },
          {
            "center": 9,
            "left": 2,
            "right": 10,
            "row_index": 5
          },
          {
            "center": 9,
            "left": 2,
            "right": 11,
            "row_index": 5
          },
          {
            "center": 10,
            "left": 0,
            "right": 7,
            "row_index": 6
          },
          {
            "center": 10,
            "left": 0,
            "right": 11,
            "row_index": 6
          },
          {
            "center": 11,
            "left": 0,
            "right": 1,
            "row_index": 7
          },
          {
            "center": 11,
            "left": 0,
            "right": 5,
            "row_index": 7
          },
          {
            "center": 11,
            "left": 0,
            "right": 6,
            "row_index": 7
          }
        ],
        "retained_equalities_sha256": "b26d1fe5118622817427866f84e8d6e80b4ec5c30b7c89007cf6f50c9243e439",
        "retained_equality_count": 20,
        "status": "CROSSCHECKED_UNIT_EQUALITY_SUBSYSTEM",
        "strategy": "repeated-greedy-equality-deletion-msolve-proposal-singular-confirmation",
        "wall_budget_seconds": 240.0
      },
      "shard_index": 1,
      "source_witness_sha256": "4246b50080baabbfbaeb9b6f87b4a446d90f75dadf0d2d677d35aba2ace1a6cf"
    },
    {
      "input_row_deletion_complete": false,
      "input_row_irredundant": false,
      "input_rows": [
        {
          "center": 0,
          "support": [
            1,
            2,
            3,
            4
          ]
        },
        {
          "center": 4,
          "support": [
            0,
            5,
            10,
            11
          ]
        },
        {
          "center": 5,
          "support": [
            0,
            1,
            8,
            9
          ]
        },
        {
          "center": 6,
          "support": [
            2,
            5,
            9,
            10
          ]
        },
        {
          "center": 8,
          "support": [
            0,
            3,
            5,
            7
          ]
        },
        {
          "center": 9,
          "support": [
            3,
            6,
            8,
            10
          ]
        },
        {
          "center": 10,
          "support": [
            1,
            7,
            8,
            11
          ]
        },
        {
          "center": 11,
          "support": [
            1,
            5,
            6,
            9
          ]
        }
      ],
      "input_rows_sha256": "219339e0a135d9a5c5b2c07693736c775e4018196ad89341be81efa6aa9117d8",
      "minimization": {
        "attempt_count": 38,
        "attempts_sha256": "f0ab86bf5d24bb9046938e1558ecc6bc78e0c487edbc45d6c9819fd0da503b74",
        "budget_exhausted": false,
        "completed_passes": 2,
        "final_crosscheck": {
          "msolve_qq_forward_variables": {
            "verdict": "UNIT"
          },
          "msolve_qq_reverse_variables": {
            "verdict": "UNIT"
          },
          "singular_qq": {
            "verdict": "UNIT"
          },
          "status": "CROSSCHECKED_UNIT"
        },
        "initial_crosscheck": {
          "msolve_qq_forward_variables": {
            "verdict": "UNIT"
          },
          "msolve_qq_reverse_variables": {
            "verdict": "UNIT"
          },
          "singular_qq": {
            "verdict": "UNIT"
          },
          "status": "CROSSCHECKED_UNIT"
        },
        "initial_equality_count": 24,
        "retained_equalities": [
          {
            "center": 0,
            "left": 1,
            "right": 4,
            "row_index": 0
          },
          {
            "center": 4,
            "left": 0,
            "right": 5,
            "row_index": 1
          },
          {
            "center": 4,
            "left": 0,
            "right": 10,
            "row_index": 1
          },
          {
            "center": 4,
            "left": 0,
            "right": 11,
            "row_index": 1
          },
          {
            "center": 5,
            "left": 0,
            "right": 1,
            "row_index": 2
          },
          {
            "center": 5,
            "left": 0,
            "right": 8,
            "row_index": 2
          },
          {
            "center": 5,
            "left": 0,
            "right": 9,
            "row_index": 2
          },
          {
            "center": 8,
            "left": 0,
            "right": 5,
            "row_index": 4
          },
          {
            "center": 9,
            "left": 3,
            "right": 8,
            "row_index": 5
          },
          {
            "center": 9,
            "left": 3,
            "right": 10,
            "row_index": 5
          },
          {
            "center": 10,
            "left": 1,
            "right": 8,
            "row_index": 6
          },
          {
            "center": 10,
            "left": 1,
            "right": 11,
            "row_index": 6
          },
          {
            "center": 11,
            "left": 1,
            "right": 5,
            "row_index": 7
          },
          {
            "center": 11,
            "left": 1,
            "right": 9,
            "row_index": 7
          }
        ],
        "retained_equalities_sha256": "5985a2c8d45eb26746e9758390df2a87042385090c9a94b001c08e9e8e6eaa8c",
        "retained_equality_count": 14,
        "status": "CROSSCHECKED_UNIT_EQUALITY_SUBSYSTEM",
        "strategy": "repeated-greedy-equality-deletion-msolve-proposal-singular-confirmation",
        "wall_budget_seconds": 240.0
      },
      "shard_index": 14,
      "source_witness_sha256": "8436bdb8973a549737e69d759e7f6411c85d9872160c9247c33d863b9c2a4091"
    },
    {
      "input_row_deletion_complete": false,
      "input_row_irredundant": false,
      "input_rows": [
        {
          "center": 0,
          "support": [
            1,
            2,
            3,
            4
          ]
        },
        {
          "center": 2,
          "support": [
            0,
            4,
            9,
            10
          ]
        },
        {
          "center": 3,
          "support": [
            4,
            6,
            7,
            10
          ]
        },
        {
          "center": 5,
          "support": [
            2,
            6,
            9,
            11
          ]
        },
        {
          "center": 8,
          "support": [
            0,
            2,
            5,
            11
          ]
        },
        {
          "center": 9,
          "support": [
            1,
            6,
            10,
            11
          ]
        },
        {
          "center": 10,
          "support": [
            3,
            7,
            9,
            11
          ]
        },
        {
          "center": 11,
          "support": [
            0,
            1,
            5,
            7
          ]
        }
      ],
      "input_rows_sha256": "4c4c25b51c3c9f7f4262a2ee6d60cced1475e89bcfc12d0d3d40e447a0f012e7",
      "minimization": {
        "attempt_count": 21,
        "attempts_sha256": "91318dbfa7faab3b996f0b2595ebdba8564110ffc271bbcca9d7fded5e16e7cf",
        "budget_exhausted": true,
        "completed_passes": 2,
        "final_crosscheck": {
          "msolve_qq_forward_variables": {
            "verdict": "UNIT"
          },
          "msolve_qq_reverse_variables": {
            "verdict": "UNIT"
          },
          "singular_qq": {
            "verdict": "UNIT"
          },
          "status": "CROSSCHECKED_UNIT"
        },
        "initial_crosscheck": {
          "msolve_qq_forward_variables": {
            "verdict": "UNIT"
          },
          "msolve_qq_reverse_variables": {
            "verdict": "UNIT"
          },
          "singular_qq": {
            "verdict": "UNIT"
          },
          "status": "CROSSCHECKED_UNIT"
        },
        "initial_equality_count": 24,
        "retained_equalities": [
          {
            "center": 0,
            "left": 1,
            "right": 2,
            "row_index": 0
          },
          {
            "center": 0,
            "left": 1,
            "right": 4,
            "row_index": 0
          },
          {
            "center": 2,
            "left": 0,
            "right": 4,
            "row_index": 1
          },
          {
            "center": 2,
            "left": 0,
            "right": 9,
            "row_index": 1
          },
          {
            "center": 2,
            "left": 0,
            "right": 10,
            "row_index": 1
          },
          {
            "center": 3,
            "left": 4,
            "right": 6,
            "row_index": 2
          },
          {
            "center": 3,
            "left": 4,
            "right": 7,
            "row_index": 2
          },
          {
            "center": 3,
            "left": 4,
            "right": 10,
            "row_index": 2
          },
          {
            "center": 5,
            "left": 2,
            "right": 6,
            "row_index": 3
          },
          {
            "center": 5,
            "left": 2,
            "right": 9,
            "row_index": 3
          },
          {
            "center": 5,
            "left": 2,
            "right": 11,
            "row_index": 3
          },
          {
            "center": 8,
            "left": 0,
            "right": 2,
            "row_index": 4
          },
          {
            "center": 8,
            "left": 0,
            "right": 5,
            "row_index": 4
          },
          {
            "center": 8,
            "left": 0,
            "right": 11,
            "row_index": 4
          },
          {
            "center": 9,
            "left": 1,
            "right": 6,
            "row_index": 5
          },
          {
            "center": 9,
            "left": 1,
            "right": 10,
            "row_index": 5
          },
          {
            "center": 9,
            "left": 1,
            "right": 11,
            "row_index": 5
          },
          {
            "center": 10,
            "left": 3,
            "right": 7,
            "row_index": 6
          },
          {
            "center": 10,
            "left": 3,
            "right": 9,
            "row_index": 6
          },
          {
            "center": 10,
            "left": 3,
            "right": 11,
            "row_index": 6
          },
          {
            "center": 11,
            "left": 0,
            "right": 1,
            "row_index": 7
          },
          {
            "center": 11,
            "left": 0,
            "right": 5,
            "row_index": 7
          },
          {
            "center": 11,
            "left": 0,
            "right": 7,
            "row_index": 7
          }
        ],
        "retained_equalities_sha256": "a50c510e99d18b4bccc5caa803f51d01bb524d93874596c497a6713c78c403a1",
        "retained_equality_count": 23,
        "status": "CROSSCHECKED_UNIT_EQUALITY_SUBSYSTEM",
        "strategy": "repeated-greedy-equality-deletion-msolve-proposal-singular-confirmation",
        "wall_budget_seconds": 240.0
      },
      "shard_index": 18,
      "source_witness_sha256": "fa2319a24b2dc3724339d5e740160df4968ee42ca066bd1cc2d1d952e6c2bf24"
    }
  ],
  "configuration": {
    "call_timeout_seconds": 12.0,
    "wall_budget_seconds_per_case": 240.0,
    "workers": 3
  },
  "schema": "p97-atail-formalized-core-shard-equality-minimization-v1",
  "scope": {
    "card_11_included": false,
    "fixed_placement_only": true,
    "formalized_metric_core_bank_clean": true,
    "nullstellensatz_certificate_replayed": false,
    "producer_proved": false,
    "target_faithful": false,
    "trusted_exact_cas_computation": true
  },
  "selection": {
    "case_count": 3,
    "retained_row_count": 8
  },
  "source_checkpoint": "scratch/atail-force/second_center_query/formalized_core_shards_after_seven_point_six_circle_oracle_checkpoint.json",
  "source_checkpoint_sha256": "2bdfa1a62fea79fa2c18d379dad4b7f609fc0465cae2e35dfb539a436d8de211"
}
