{
  "alpha": [
    "0",
    "-18",
    "7",
    "-25",
    "0",
    "-25",
    "0",
    "-25",
    "0",
    "-25"
  ],
  "beta": [
    "50",
    "82",
    "57",
    "75",
    "50",
    "75",
    "50",
    "63",
    "50",
    "75"
  ],
  "edges": [
    [0, 2],
    [0, 5],
    [0, 7],
    [0, 8],
    [1, 0],
    [1, 3],
    [1, 5],
    [1, 9],
    [2, 0],
    [2, 4],
    [2, 6],
    [2, 8],
    [3, 1],
    [3, 2],
    [3, 4],
    [3, 5],
    [4, 2],
    [4, 6],
    [4, 7],
    [4, 9],
    [5, 1],
    [5, 3],
    [5, 4],
    [5, 6],
    [6, 2],
    [6, 4],
    [6, 8],
    [7, 1],
    [7, 5],
    [7, 6],
    [7, 8],
    [7, 9],
    [8, 0],
    [8, 2],
    [8, 3],
    [8, 6],
    [9, 0],
    [9, 1],
    [9, 8]
  ],
  "epistemic_status": "EXACT_RATIONAL_COUNTEREXAMPLE",
  "n": 10,
  "schema": "p97-positive-circular-split-additive-tight-graph-counterexample-v1",
  "weights": [
    "1",
    "5",
    "1",
    "1",
    "5",
    "5",
    "14",
    "10",
    "1",
    "1",
    "1",
    "1",
    "1",
    "10",
    "14",
    "9",
    "1",
    "1",
    "1",
    "5",
    "2",
    "5",
    "1",
    "1",
    "1",
    "6",
    "1",
    "1",
    "1",
    "10",
    "1",
    "1",
    "6",
    "1",
    "6"
  ]
}
